docassemble.ILAOEfile-1.0.4-py3.10-nspkg.pth
docassemble/ILAOEfile/__init__.py
docassemble/ILAOEfile/docs_list.py
docassemble/ILAOEfile/ilao_easy_forms_database.py
docassemble/ILAOEfile/ilao_tools.py
docassemble/ILAOEfile/toolbox.py
docassemble/ILAOEfile/data/questions/default-home.yml
docassemble/ILAOEfile/data/questions/efile-account-interview.yml
docassemble/ILAOEfile/data/questions/feedback.yml
docassemble/ILAOEfile/data/questions/ilao-interview-framework.yml
docassemble/ILAOEfile/data/questions/ilao_interview_list.yml
docassemble/ILAOEfile/data/questions/shared-basic-questions.yml
docassemble/ILAOEfile/data/questions/toga_payments_interview.yml
docassemble/ILAOEfile/data/sources/README.md
docassemble/ILAOEfile/data/sources/il_courts.xlsx
docassemble/ILAOEfile/data/sources/ilao_docassemble_easy_forms.xlsx
docassemble/ILAOEfile/data/static/README.md
docassemble/ILAOEfile/data/static/android-chrome-192x192.png
docassemble/ILAOEfile/data/static/android-chrome-512x512.png
docassemble/ILAOEfile/data/static/apple-touch-icon.png
docassemble/ILAOEfile/data/static/browserconfig.xml
docassemble/ILAOEfile/data/static/case_number.png
docassemble/ILAOEfile/data/static/favicon-16x16.png
docassemble/ILAOEfile/data/static/favicon-32x32.png
docassemble/ILAOEfile/data/static/favicon.ico
docassemble/ILAOEfile/data/static/force_lightmode.js
docassemble/ILAOEfile/data/static/ilao.logo.21.svg
docassemble/ILAOEfile/data/static/ilao.logo.new.svg
docassemble/ILAOEfile/data/static/ilao.logo.noname.25.png
docassemble/ILAOEfile/data/static/ilao.logo.svg
docassemble/ILAOEfile/data/static/ilao_docs_table.css
docassemble/ILAOEfile/data/static/ilao_theme_2.css
docassemble/ILAOEfile/data/static/logo1.png
docassemble/ILAOEfile/data/static/logo1.svg
docassemble/ILAOEfile/data/static/logo2.svg
docassemble/ILAOEfile/data/static/logo_gray_26.svg
docassemble/ILAOEfile/data/static/logo_white_26.svg
docassemble/ILAOEfile/data/static/logo_white_30.svg
docassemble/ILAOEfile/data/static/manifest.json
docassemble.ILAOEfile-1.0.4.dist-info/LICENSE
docassemble.ILAOEfile-1.0.4.dist-info/METADATA
docassemble.ILAOEfile-1.0.4.dist-info/WHEEL
docassemble.ILAOEfile-1.0.4.dist-info/namespace_packages.txt
docassemble.ILAOEfile-1.0.4.dist-info/top_level.txt
docassemble.ILAOEfile-1.0.4.dist-info/RECORD
