Metadata-Version: 2.1
Name: docassemble.ILAOEfile
Version: 1.0.4
Summary: A docassemble extension.
Home-page: https://docassemble.org
Author: Matt Newsted
Author-email: formsupport@illinoislegalaid.org
License: The MIT License (MIT)
License-File: LICENSE
Requires-Dist: docassemble.AssemblyLine
Requires-Dist: docassemble.ALToolbox
Requires-Dist: docassemble.EFSPIntegration
